bk_plugin_runtime/__init__.py
bk_plugin_runtime/__version__.py
bk_plugin_runtime/config/__init__.py
bk_plugin_runtime/config/default.py
bk_plugin_runtime/config/dev.py
bk_plugin_runtime/config/prod.py
bk_plugin_runtime/config/stag.py
bk_plugin_runtime/manage.py
bk_plugin_runtime/packages/apigw/__init__.py
bk_plugin_runtime/packages/apigw/backends.py
bk_plugin_runtime/packages/open/blueking/__init__.py
bk_plugin_runtime/packages/open/blueking/component/README.md
bk_plugin_runtime/packages/open/blueking/component/__init__.py
bk_plugin_runtime/packages/open/blueking/component/apis/__init__.py
bk_plugin_runtime/packages/open/blueking/component/apis/bk_login.py
bk_plugin_runtime/packages/open/blueking/component/apis/bk_paas.py
bk_plugin_runtime/packages/open/blueking/component/apis/cc.py
bk_plugin_runtime/packages/open/blueking/component/apis/cmsi.py
bk_plugin_runtime/packages/open/blueking/component/apis/gse.py
bk_plugin_runtime/packages/open/blueking/component/apis/itsm.py
bk_plugin_runtime/packages/open/blueking/component/apis/job.py
bk_plugin_runtime/packages/open/blueking/component/apis/jobv3.py
bk_plugin_runtime/packages/open/blueking/component/apis/monitor_v3.py
bk_plugin_runtime/packages/open/blueking/component/apis/sops.py
bk_plugin_runtime/packages/open/blueking/component/apis/usermanage.py
bk_plugin_runtime/packages/open/blueking/component/base.py
bk_plugin_runtime/packages/open/blueking/component/client.py
bk_plugin_runtime/packages/open/blueking/component/collections.py
bk_plugin_runtime/packages/open/blueking/component/compat.py
bk_plugin_runtime/packages/open/blueking/component/conf.py
bk_plugin_runtime/packages/open/blueking/component/exceptions.py
bk_plugin_runtime/packages/open/blueking/component/shortcuts.py
bk_plugin_runtime/packages/open/blueking/component/utils.py
bk_plugin_runtime/packages/open/blueking/tests/README.md
bk_plugin_runtime/packages/open/blueking/tests/__init__.py
bk_plugin_runtime/packages/open/blueking/tests/test_client.py
bk_plugin_runtime-2.1.4.dist-info/METADATA
bk_plugin_runtime-2.1.4.dist-info/WHEEL
bk_plugin_runtime-2.1.4.dist-info/RECORD
