Metadata-Version: 2.1
Name: bk-plugin-runtime
Version: 2.1.4
Summary: bk plugin python django runtime
License: MIT
Author: Your Name
Author-email: you@example.com
Requires-Python: >=3.8.0,<4.0.0
Classifier: License :: OSI Approved :: MIT License
Classifier: Programming Language :: Python :: 3
Classifier: Programming Language :: Python :: 3.8
Classifier: Programming Language :: Python :: 3.9
Classifier: Programming Language :: Python :: 3.10
Classifier: Programming Language :: Python :: 3.11
Classifier: Programming Language :: Python :: 3.12
Classifier: Programming Language :: Python :: 3.13
Requires-Dist: Django (>=2.2.6,<5)
Requires-Dist: blueapps[opentelemetry] (>=4.15.1,<5.0)
Requires-Dist: celery (>=5.4.0,<6.0.0)
Requires-Dist: ddtrace (>=0.14.1,<0.15.0)
Requires-Dist: django-celery-beat (>=2.7.0,<3.0.0)
Requires-Dist: django-celery-results (>=2.5.1,<3.0.0)
Requires-Dist: django-cors-headers (>=4.0.0,<5.0.0)
Requires-Dist: django-dbconn-retry (>=0.1.5,<0.2.0)
Requires-Dist: djangorestframework (>=3.15,<4.0)
Requires-Dist: drf-yasg (>=1.21.5,<2.0.0)
Requires-Dist: gunicorn (>=19.6.0)
Requires-Dist: protobuf (>=3.19.4,<6.0)
Requires-Dist: pymysql (>=1,<2)
Requires-Dist: raven (>=6.5.0,<7.0.0)
Requires-Dist: redis (>=2.10.5,<6)
